{
  "id": "what_you_need",
  "title": "What You Need to Play",
  "category": "Basics",
  "keywords": ["components", "dice", "deck", "tokens"],
  "content": "To play Moonstone, in addition to these rules you will need:\n• 2–4 players\n• A 3’ by 3’ playing surface with fantasy terrain\n• 3–6 **Moonstone Miniatures** for each player, with accompanying **Character Cards**.\n• A tape measure or precision measuring instrument(s)\n• A 21-card **Arcane Deck**\n• An 18-card **Melee Deck**\n• A pile of small blue disks to use as **Energy Tokens**\n• 7x four-sided dice to act as **Moonstones**\n• 1x six-sided die for each player",
  "searchable": false
}
